{
  "color": {
    "background": {
      "layout": {
        "weakest": {
          "$type": "color",
          "$value": "#999999ff"
        },
        "weaker": {
          "$type": "color",
          "$value": "#aaaaaaff"
        },
        "weak": {
          "$type": "color",
          "$value": "#bbbbbbff"
        },
        "normal": {
          "$type": "color",
          "$value": "#ccccccff"
        },
        "strong": {
          "$type": "color",
          "$value": "#ddddddff"
        },
        "stronger": {
          "$type": "color",
          "$value": "#eeeeeeff"
        },
        "strongest": {
          "$type": "color",
          "$value": "#ffffffff"
        }
      }
    },
    "text": {
      "layout": {
        "strongest": {
          "$type": "color",
          "$value": "#000000ff"
        }
      }
    }
  }
}
